colorthistext/__init__.py
colorthistext/colorthistext.py
colorthistext-0.2.dist-info/METADATA
colorthistext-0.2.dist-info/WHEEL
colorthistext-0.2.dist-info/top_level.txt
colorthistext-0.2.dist-info/RECORD
