Metadata-Version: 2.1
Name: colorthistext
Version: 0.2
Summary: Lib to color text.
Home-page: https://gitlab.com/kelvium/colorthistext
Author: Kelvium
Author-email: contact@kelvium.design
License: MIT
Platform: UNKNOWN
